met_api/__init__.py
met_api/functional.py
met_api/response_objects.py
met_api/utils.py
met_api-0.1.1.dist-info/LICENSE
met_api-0.1.1.dist-info/WHEEL
met_api-0.1.1.dist-info/METADATA
met_api-0.1.1.dist-info/RECORD
