Metadata-Version: 2.1
Name: met-api
Version: 0.1.1
Summary: "Metropolitain Museum of Art API client."
License: GPLv3
Author: Yevhenii Zotkin
Author-email: yevhenii.zotkin@protonmail.com
Requires-Python: >=3.8,<4.0
Classifier: License :: Other/Proprietary License
Classifier: Programming Language :: Python :: 3
Classifier: Programming Language :: Python :: 3.8
Classifier: Programming Language :: Python :: 3.9
Requires-Dist: pydantic (>=1.6.1,<2.0.0)
Requires-Dist: requests (>=2.24.0,<3.0.0)
